abstract_parallels/__init__.py
abstract_parallels/parallels_control_center.py
abstract_parallels/parallels_setup.sh
abstract_parallels/run_api_gui.sh
abstract_parallels/apis/__init__.py
abstract_parallels/apis/api_gui.py
abstract_parallels/apis/run_api_gui.sh
abstract_parallels/clipit/__init__.py
abstract_parallels/clipit/get_clipit.py
abstract_parallels/clipit/run_clipit_gui.sh
abstract_parallels/services_mgr/__init__.py
abstract_parallels/services_mgr/run_service_manager.sh
abstract_parallels/services_mgr/servicesManager.py
abstract_parallels/window_mgr/__init__.py
abstract_parallels/window_mgr/get_window_mgr.py
abstract_parallels/window_mgr/run_clipit_window_mgr.sh
abstract_parallels-0.0.405.dist-info/METADATA
abstract_parallels-0.0.405.dist-info/WHEEL
abstract_parallels-0.0.405.dist-info/top_level.txt
abstract_parallels-0.0.405.dist-info/RECORD
